Metadata-Version: 1.1
Name: g2gtools
Version: 0.2.7
Summary: A suite of tools for the reconstruction of personal diploid genomes and better coordinate conversion
Home-page: http://churchill-lab.github.io/g2gtools/
Author: Matthew J. Vincent and Kwangbom "KB" Choi, The Jackson Laboratory
Author-email: kb.choi@jax.org
License: MIT
Keywords: g2gtools,personal genomes,liftover
Platform: UNKNOWN
Classifier: Development Status :: 4 - Beta
Classifier: Intended Audience :: Developers
Classifier: Intended Audience :: Science/Research
Classifier: License :: OSI Approved :: MIT License
Classifier: Natural Language :: English
Classifier: Programming Language :: Python :: 2
Classifier: Programming Language :: Python :: 2.7
Classifier: Programming Language :: Python :: 3
Classifier: Programming Language :: Python :: 3.5
Classifier: Programming Language :: Python :: 3.6
